{
  "events": [
    {
      "id": "im-1",
      "name": "IM Event 1",
      "fullName": "Mick McGoldrick Individual Membership - Area Draw 1",
      "type": "im",
      "status": "active",
      "format": "First to 7 frames",
      "qualifiers": 2,
      "finals": "25th & 26th April 2026",
      "finalsVenue": "Corner Pocket, Dalkeith",
      "hasSpreadsheet": true,
      "drawAvailable": true
    },
    {
      "id": "im-2",
      "name": "IM Event 2",
      "fullName": "Individual Membership - Area Draw 2",
      "type": "im",
      "status": "upcoming",
      "format": "First to 7 frames",
      "qualifiers": 2,
      "finals": "20th & 21st June 2026",
      "finalsVenue": "TBC",
      "hasSpreadsheet": false,
      "drawAvailable": false
    },
    {
      "id": "im-3",
      "name": "IM Event 3",
      "fullName": "Individual Membership - Area Draw 3",
      "type": "im",
      "status": "upcoming",
      "format": "First to 7 frames",
      "qualifiers": 2,
      "finals": "1st & 2nd August 2026",
      "finalsVenue": "TBC",
      "hasSpreadsheet": false,
      "drawAvailable": false
    },
    {
      "id": "im-4",
      "name": "IM Event 4",
      "fullName": "Individual Membership - Area Draw 4",
      "type": "im",
      "status": "upcoming",
      "format": "First to 7 frames",
      "qualifiers": 2,
      "finals": "3rd & 4th October 2026",
      "finalsVenue": "TBC",
      "hasSpreadsheet": false,
      "drawAvailable": false
    },
    {
      "id": "willie-mccartney",
      "name": "Willie McCartney Trophy",
      "fullName": "2026 Willie McCartney Trophy",
      "type": "trophy",
      "status": "upcoming",
      "format": "Races to 6",
      "qualifiers": 2,
      "finals": "27th & 28th June 2026",
      "finalsVenue": "McGurtys, Dundee",
      "entryFee": "£5 per player (+£5 if not SPA registered for 2025)",
      "entryDeadline": "Friday 27th March 2026 at 21:00",
      "hasSpreadsheet": false,
      "drawAvailable": false,
      "notes": "Tournament Committee reviews all entries. Those previously ineligible remain ineligible.",
      "dumfriesEntries": ["Owen Bruce", "Rich Cooper", "Jayde Devlin", "Sean Rutherford", "Gav Hunter", "Mark Lockhart", "Derek Reid"]
    }
  ]
}
